build/lib/saxviz/__init__.py
build/lib/saxviz/saxviz.py
saxviz/__init__.py
saxviz/saxviz.py
saxviz/html/index.html
saxviz/html/static/css/normalize.css
saxviz/html/static/css/skeleton.css
saxviz/html/static/images/favicon.png
saxviz/html/static/js/.gitignore
saxviz/html/static/js/js-yaml.min.js
saxviz/html/static/js/schemedit.js
saxviz/html/static/js/schemeditclient.js
saxviz/html/static/wasm/.gitignore
saxviz/html/static/wasm/schemedit.wasm
saxviz-0.0.0.dist-info/LICENSE
saxviz-0.0.0.dist-info/METADATA
saxviz-0.0.0.dist-info/WHEEL
saxviz-0.0.0.dist-info/top_level.txt
saxviz-0.0.0.dist-info/RECORD
