Metadata-Version: 2.1
Name: saxviz
Version: 0.0.0
Summary: Schematic Visualizer for SAX
Author-email: Floris Laporte <floris.laporte@gmail.com>
Classifier: Development Status :: 3 - Alpha
Classifier: Intended Audience :: Science/Research
Classifier: License :: OSI Approved :: Apache Software License
Classifier: Operating System :: OS Independent
Classifier: Programming Language :: Python :: 3.9
Classifier: Programming Language :: Python :: 3.10
Classifier: Programming Language :: Python :: 3.11
Classifier: Programming Language :: Python :: 3.12
Classifier: Topic :: Scientific/Engineering
Classifier: Topic :: Scientific/Engineering :: Physics
Requires-Python: >=3.9.0
License-File: LICENSE
Requires-Dist: sax
Requires-Dist: websockets
